setup.py
pagarme_integration/__init__.py
pagarme_integration/payment_gateway.py
pagarme_integration.egg-info/PKG-INFO
pagarme_integration.egg-info/SOURCES.txt
pagarme_integration.egg-info/dependency_links.txt
pagarme_integration.egg-info/not-zip-safe
pagarme_integration.egg-info/requires.txt
pagarme_integration.egg-info/top_level.txt
pagarme_integration/classes/__init__.py
pagarme_integration/classes/balance.py
pagarme_integration/classes/bank_account.py
pagarme_integration/classes/cards.py
pagarme_integration/classes/config.py
pagarme_integration/classes/customers.py
pagarme_integration/classes/orders.py
pagarme_integration/classes/recipients.py
pagarme_integration/classes/withdraw.py
pagarme_integration/schemas/__init__.py
pagarme_integration/schemas/address.py
pagarme_integration/schemas/automatic_anticipation_settings.py
pagarme_integration/schemas/balance.py
pagarme_integration/schemas/cards.py
pagarme_integration/schemas/charges.py
pagarme_integration/schemas/customers.py
pagarme_integration/schemas/default_bank_account.py
pagarme_integration/schemas/errors.py
pagarme_integration/schemas/gateway_responses.py
pagarme_integration/schemas/items.py
pagarme_integration/schemas/orders.py
pagarme_integration/schemas/payments.py
pagarme_integration/schemas/phone.py
pagarme_integration/schemas/pix.py
pagarme_integration/schemas/recipients.py
pagarme_integration/schemas/transactions.py
pagarme_integration/schemas/transfer_settings.py
pagarme_integration/schemas/withdraw.py
pagarme_integration/utils/__init__.py
pagarme_integration/utils/handle_errors.py