Metadata-Version: 1.1
Name: pagarme-integration
Version: 0.2.4
Summary: Pagarme API
Home-page: https://github.com/caiquilipe/pagarme_integration.git
Author: Caiqui Fhelipe and Juan Pablo
Author-email: developer.cfms@gmail.com
License: UNKNOWN
Download-URL: https://github.com/caiquilipe/pagarme_integration.git
Platform: UNKNOWN
